primitiv-0.4.0.dev231.data/data/lib/libprimitiv.a
primitiv-0.4.0.dev231.data/data/include/primitiv/primitiv.h
primitiv-0.4.0.dev231.data/data/include/primitiv/version.h
primitiv-0.4.0.dev231.data/data/include/primitiv/config.h
primitiv-0.4.0.dev231.data/data/include/primitiv/contrib/functions.h
primitiv-0.4.0.dev231.data/data/include/primitiv/msgpack/reader.h
primitiv-0.4.0.dev231.data/data/include/primitiv/msgpack/writer.h
primitiv-0.4.0.dev231.data/data/include/primitiv/msgpack/objects.h
primitiv-0.4.0.dev231.data/data/include/primitiv/core/functions.h
primitiv-0.4.0.dev231.data/data/include/primitiv/core/spinlock.h
primitiv-0.4.0.dev231.data/data/include/primitiv/core/file_format.h
primitiv-0.4.0.dev231.data/data/include/primitiv/core/initializer_impl.h
primitiv-0.4.0.dev231.data/data/include/primitiv/core/numeric_utils.h
primitiv-0.4.0.dev231.data/data/include/primitiv/core/model.h
primitiv-0.4.0.dev231.data/data/include/primitiv/core/memory_pool.h
primitiv-0.4.0.dev231.data/data/include/primitiv/core/tensor.h
primitiv-0.4.0.dev231.data/data/include/primitiv/core/operator.h
primitiv-0.4.0.dev231.data/data/include/primitiv/core/string_utils.h
primitiv-0.4.0.dev231.data/data/include/primitiv/core/basic_functions.h
primitiv-0.4.0.dev231.data/data/include/primitiv/core/type_traits.h
primitiv-0.4.0.dev231.data/data/include/primitiv/core/random.h
primitiv-0.4.0.dev231.data/data/include/primitiv/core/optimizer.h
primitiv-0.4.0.dev231.data/data/include/primitiv/core/optimizer_impl.h
primitiv-0.4.0.dev231.data/data/include/primitiv/core/parameter.h
primitiv-0.4.0.dev231.data/data/include/primitiv/core/shape.h
primitiv-0.4.0.dev231.data/data/include/primitiv/core/operator_impl.h
primitiv-0.4.0.dev231.data/data/include/primitiv/core/graph.h
primitiv-0.4.0.dev231.data/data/include/primitiv/core/initializer.h
primitiv-0.4.0.dev231.data/data/include/primitiv/core/arithmetic.h
primitiv-0.4.0.dev231.data/data/include/primitiv/core/shape_ops.h
primitiv-0.4.0.dev231.dist-info/RECORD
primitiv-0.4.0.dev231.dist-info/top_level.txt
primitiv-0.4.0.dev231.dist-info/WHEEL
primitiv-0.4.0.dev231.dist-info/METADATA
