Metadata-Version: 2.1
Name: primitiv
Version: 0.4.0.dev231
Summary: primitiv: A Neural Network Toolkit. (Python frontend)
Home-page: https://github.com/primitiv/primitiv-python
Author: primitiv developer group
Author-email: primitiv-developer-group@googlegroups.com
License: UNKNOWN
Platform: UNKNOWN
Classifier: Development Status :: 3 - Alpha
Classifier: Intended Audience :: Developers
Classifier: Intended Audience :: Science/Research
Classifier: License :: OSI Approved :: Apache Software License
Classifier: Operating System :: POSIX
Classifier: Programming Language :: C++
Classifier: Programming Language :: Python :: 3
Classifier: Topic :: Scientific/Engineering :: Artificial Intelligence
Requires-Dist: numpy (>=1.16.1)
